Metadata-Version: 1.0
Name: DistributionsInheritanceAN
Version: 1.2
Summary: Gaussian Binomial distributions
Home-page: UNKNOWN
Author:  Aymar A. NAHUM 
Author-email: postmaster@jecorde.net
License: UNKNOWN
Platform: UNKNOWN
